README.md
setup.py
files/gxenv
gxenv/__init__.py
gxenv/__main__.py
gxenv/cli.py
gxenv/const.py
gxenv.egg-info/PKG-INFO
gxenv.egg-info/SOURCES.txt
gxenv.egg-info/dependency_links.txt
gxenv.egg-info/requires.txt
gxenv.egg-info/top_level.txt