Metadata-Version: 2.1
Name: gxenv
Version: 0.2.1
Summary: a GX-flavored venv wrapper
Home-page: UNKNOWN
Author: GROOVE X Development Team
Author-email: dev@groove-x.com
License: UNKNOWN
Platform: UNKNOWN
Provides-Extra: dev
